snmpkit/__init__.py
snmpkit/agent/__init__.py
snmpkit/agent/agent.py
snmpkit/agent/exceptions.py
snmpkit/agent/handlers.py
snmpkit/agent/protocol.py
snmpkit/agent/set_handler.py
snmpkit/agent/updater.py
snmpkit/core.cpython-314-x86_64-linux-gnu.so
snmpkit/core.pyi
snmpkit-1.0.0.dist-info/METADATA
snmpkit-1.0.0.dist-info/WHEEL
snmpkit-1.0.0.dist-info/licenses/LICENSE
snmpkit-1.0.0.dist-info/RECORD
