Metadata-Version: 2.4
Name: snmpkit
Version: 1.0.0
Classifier: Development Status :: 5 - Production/Stable
Classifier: Intended Audience :: Developers
Classifier: Intended Audience :: System Administrators
Classifier: License :: OSI Approved :: GNU Affero General Public License v3 or later (AGPLv3+)
Classifier: Operating System :: POSIX :: Linux
Classifier: Programming Language :: Python :: 3.14
Classifier: Programming Language :: Rust
Classifier: Topic :: System :: Networking :: Monitoring
Classifier: Topic :: System :: Systems Administration
Classifier: Typing :: Typed
Requires-Dist: uvloop>=0.21
Requires-Dist: pytest>=8.0 ; extra == 'dev'
Requires-Dist: pytest-asyncio>=0.24 ; extra == 'dev'
Requires-Dist: pytest-xdist>=3.5 ; extra == 'dev'
Requires-Dist: ruff>=0.9 ; extra == 'dev'
Provides-Extra: dev
License-File: LICENSE
Summary: High-performance SNMP toolkit with Rust core - AgentX subagent and SNMP manager
Keywords: snmp,agentx,network,monitoring,rust
License-Expression: AGPL-3.0-or-later
Requires-Python: >=3.14
Project-URL: Changelog, https://github.com/darhebkf/snmpkit/blob/main/CHANGELOG.md
Project-URL: Documentation, https://snmpkit.dev
Project-URL: Homepage, https://snmpkit.dev
Project-URL: Issues, https://github.com/darhebkf/snmpkit/issues
Project-URL: Repository, https://github.com/darhebkf/snmpkit
